{"date":"2026-05-15","version":1,"grid":["טההק","נדתח","משפי","תיסל"],"answers":["דפימ","הדפס","הדפסימ","הנשימ","התדמית","התחיל","חיסל","חיפש","חיפשת","חיפשתי","חיפשתמ","חפימ","חפשי","יחפש","יסיח","יפיל","יפימ","יפתח","ישנה","ישנמ","ישתה","ישתפ","לפתח","מדפיס","מנטה","משנה","משפחה","משפחתי","משפיל","משתה","משתי","משתפ","משתק","מתיש","נשימ","נשית","נשמת","נשמתי","נשפימ","נשתה","נשתפ","סימנ","סליחה","סלפי","פחית","פיתה","פיתח","פיתחה","פסימ","פתחה","פתחי","פתיחה","פתיל","שמנה","שמתי","שפחה","שפתי","שתימ","תדמית","תדפיס","תחפש","תחפשי","תיפלי","תיפתח","תישנ","תפיל","תפסי","תשימ","תשנה","תשתה","תשתי","תשתפ","תשתפי"],"difficulty":"hard","counts":{"total":73,"by_length":{"5":17,"4":51,"6":5}}}