{"date":"2026-09-06","version":1,"grid":["חאימנ","ילירט","קאלנת","תטחגת","הדוכו"],"answers":["אייל","איימ","אייר","אילנ","אימנ","אירי","אירימ","אלחוט","אליי","אליל","אלילימ","אלימ","אלינ","אקיא","אקלימ","אתקל","גלאי","גליל","גלימ","גללי","גללימ","גנימ","גנרל","גנרלימ","דוגל","דחליל","התאחדו","התאימ","חוטא","חוטאימ","חטאי","חטאימ","חילק","חליל","חלימ","חללימ","חלקי","חלקת","טוגנימ","טוחנ","טלאי","טנגו","טריימ","יאיר","יחלימ","ימינ","ירימ","לאחד","לאחל","לאטה","לאיימ","לחוג","לחוד","לחטא","לחכות","ליירט","לילי","לירי","מייל","מיילל","מיינ","מילא","מילאת","מילי","מירי","מנטרל","נייר","ניירת","נילי","נרימ","נתרנ","קטלני","קטלניימ","קילל","קליל","קלימ","תאחל","תאיימ","תאימ","תאיר","תגלי","תקיא","תרימ","תרימי","תרמיל","תתני"],"difficulty":"easy","counts":{"total":86,"by_length":{"7":1,"5":21,"4":59,"6":5}}}