{"date":"2026-12-03","version":1,"grid":["גזתיג","תיטדט","תלקכי","דהווו","חיהור"],"answers":["גילה","גילו","גילוי","גילתה","דיווה","דיוק","דיור","דיכוי","דלהי","דלוק","דלוקה","דליק","דתית","הדליק","הדליקו","הדלק","הווה","הולדת","הולדתי","הולט","הוקי","הוקל","הורו","החיה","היוו","היווה","הלוכ","הקלטת","הקלטתי","הקליט","וולט","וכולי","חידה","חיוור","חיוכ","טקילה","ידחה","ידית","יהוה","יהווה","יולדת","יולי","יורו","יכול","יכולה","יכולת","יכולתי","ילדה","ילדי","ילדת","ילוו","ילווה","יתלה","יתלו","כולה","כולי","כיור","להדיח","להתיז","לווה","לוכד","לוקה","ליקוי","לקוי","לקויה","לקית","קווי","קולה","קולט","קולטת","קולי","קולית","קילו","קלוי","קלטי","קלטת","קלטתי","קליט","רווי","רווק","רווקה","רוקד","רוקדת","רוקט","תדחה","תדלוק","תדליק","תדליקו","תהווה","תהיה","תהיו","תזיק","תטיל","תיקו","תלווה","תלוי","תלויה","תליתי","תלתה","תתלה"],"difficulty":"easy","counts":{"total":100,"by_length":{"4":62,"5":33,"6":5}}}