{"date":"2026-07-08","version":1,"grid":["ושעח","משנז","יהרא","להלנ"],"answers":["אנהל","אנשימ","ארשה","ארשומ","הילה","הישנה","הישר","הנשימ","הרשה","הרשו","הרשי","הרשימ","הרשימה","הרשמה","הרשע","השמש","השרה","חזרה","ישמש","ישנא","ישנה","ישראל","ישרה","לאזנ","להישענ","להלנ","להרשימ","להשימ","לרשומ","מיהר","מילה","משנה","משרה","נאנח","נהיה","נהלי","נהלימ","נעזר","נעשה","נעשו","נעשימ","נרשה","נרשומ","נרשמ","נרשמה","נרשמו","נשומ","נשימ","נשימה","נשמה","עזרא","עזרה","עשרה","רשומ","רשומה","רשימה","רשמה","רשמו","רשמי","שומה","שושנה","שימו","שימוש","שימש","שימשו","שמשה"],"difficulty":"easy","counts":{"total":66,"by_length":{"4":43,"5":20,"6":3}}}