{"date":"2027-11-10","version":1,"grid":["יהציר","תעואא","תחאוי","נחססח","קינספ"],"answers":["אאוצ","אווה","אוויר","אויר","אוספ","אוציא","איווה","אריצ","הוואי","הוצא","הוצאו","הוציא","הוציאו","הוציאי","הוצע","הצעת","הצעתי","התחתנ","חוואי","חווה","חוצה","חסוי","חסינ","יאיר","יוסי","יוספ","יועצ","יוצא","ינחת","ינסו","יעוצ","יצאו","יראו","יתחתנ","נחוצ","נחוצה","נחנק","נחתה","נחתי","ניסו","ניסוח","ניסוי","ניקח","נסחפ","נספח","נתתי","סוחפ","סוסי","צוואר","צווארי","צווי","ראווה","ראוי","ריצה","תנחת","תניח","תנינ","תנקי","תתני"],"difficulty":"medium","counts":{"total":59,"by_length":{"5":15,"4":41,"6":3}}}