{"date":"2027-08-29","version":1,"grid":["הטמבי","צלליש","אהרלש","דתתלש","סההתש"],"answers":["אהדה","אללה","אצלה","אצלמ","אתרי","אתרימ","בייל","ביימ","בילה","בילתה","בירה","בישל","בישלה","בישלת","בליל","בלמי","בשלי","בשלימ","הטלה","הלאה","הלהט","הסתר","הסתרת","הסתתר","הצהרת","הצלה","הרימ","טמבל","יבלה","יבשימ","יירה","יישב","ילבש","ימלא","ירתה","ישימ","ישיר","ישירה","לאתר","לביימ","לבייש","לבשי","לבשל","להלביש","להלל","להצטלמ","להרימ","לייב","לייבש","ליישב","לילה","למטה","למלא","לצאת","לריב","לשימ","לשיר","מבייש","מביש","מבלה","מבשל","מבשלת","מטלה","מייבש","מילה","מירה","מלאה","מלאת","צהרימ","צללימ","צלמי","שביל","שבימ","שביר","שבירה","שיירה","שילמ","שירה","שירת","שירתה","שישי","שלילה","שליש","שלישי","שתלה","שתלת","שתתה","תאלצ","תלתה","תרימ","תשלימ","תתלה"],"difficulty":"easy","counts":{"total":92,"by_length":{"4":64,"5":26,"6":2}}}