{"date":"2027-07-14","version":1,"grid":["ותאקת","טממדר","ייפלמ","ייפרר","נקזדל"],"answers":["אדמת","אמות","אמיט","אקדמי","דלפק","דמיינ","דמייני","דמימ","דממת","דפימ","דקרת","זיינ","זייפ","זינק","זקני","טיפינ","טיפל","ימות","ימימ","יפימ","לדמיינ","לדממ","למדת","למיינ","למקד","למרק","לפזר","לרדת","מאמת","מדמיינ","מדממ","מדממות","מדממת","מדפימ","מותאמ","מטיפ","מיטות","מיינ","מימי","מלמד","מלמדת","מפיק","מקדמ","מרדפ","מרפימ","מרפק","מרקמ","מרתק","מתאמ","מתמדת","מתמטי","מתמקד","מתמקדת","ניפרד","נקיימ","פייט","פיני","פינק","פיפי","פלמר","קדמי","קיימ","קיימא","קיימו","קיימות","קיימימ","קיימת","קמימ","קמפיינ","קפלר","קרמל","רקדת","רקמת","תדמיינ","תדמייני","תדממ","תומי","תמימ","תרדמת"],"difficulty":"easy","counts":{"total":79,"by_length":{"4":50,"6":9,"5":19,"7":1}}}