{"date":"2027-06-05","version":1,"grid":["דהותג","תדכתנ","ההפעמ","הפתיט","שאעפמ"],"answers":["אעיפ","אפתה","אשפה","דפימ","הודה","הודתה","הוכה","הכהה","הכפפה","הכתמ","הכתפ","הפכה","הפכו","הפכת","הפכתמ","הפעמ","הפתיע","הפתעת","הפתעתי","השפע","השפעת","התהפכ","התהפכה","התעמת","טיפה","טעימ","טעית","טעמימ","טעמת","טענת","טעתה","יטענ","ימנע","יפהפה","כהות","כפית","כפפה","כפפת","כתמימ","מטיפ","מטעמ","מטענ","מימנ","מנעת","מנעתי","מעטימ","מעטפת","מעיפ","מעיפה","מענג","מפית","מפתה","מפתיע","מתות","מתכות","מתכת","מתענג","מתעתע","מתפתה","נעימ","נעיפ","נעמי","נתתמ","עטימ","עטיפה","עמית","עמיתה","עפימ","עפתי","פיתה","פעמי","פעמימ","פעמית","שפעת","שפתי","תהודה","תהפכו","תודה","תמימ","תמנע","תמעיט","תעיפ","תפתיע"],"difficulty":"easy","counts":{"total":83,"by_length":{"4":53,"5":28,"6":2}}}