{"date":"2027-03-16","version":1,"grid":["רמשהב","יללסת","יפראמ","פכרעת","והתעמ"],"answers":["אלפי","אלפיימ","אלפימ","אסלה","ארכה","הבסת","הופכ","הופכת","הכיל","הכפיל","הכרת","הכתר","הסתמ","הפוכ","הפיכ","הפיל","הפכו","הפכת","הראתה","הרעמ","השליכ","השליכו","השלימ","השלמ","התאמת","התכופפ","התכופפי","התעמת","התרעת","ימלא","יפיל","יפימ","יפיפה","כופה","כייפ","כיפה","כיפי","כפיימ","כפיל","כפליימ","כפפה","כפרה","לאמת","לארס","להסב","להשליכ","להשלימ","למלא","לפלס","לפרסמ","לשלמ","לשמר","מאלפ","מאסר","מארס","מייל","מיילל","מילי","מלאת","מעמסה","מערה","מערכ","מערכה","מערכת","מערער","משלה","משלי","משליכ","משליכה","מתאמ","מתאר","מתארת","מתעתע","סבתא","סלפי","ערכה","ערכו","ערכי","ערכת","ערפל","פילימ","פיפי","פלייר","פלמר","פרסה","פרסמ","ראתה","שלפי","שמלה","שמרי","תהפוכ","תהפכו","תהפכי","תכפיל","תרפי"],"difficulty":"easy","counts":{"total":95,"by_length":{"4":61,"5":26,"6":7,"7":1}}}