{"date":"2027-12-21","version":1,"grid":["פשהקג","תאעסמ","תעתטמ","פרחמד","טוטטח"],"answers":["אעשה","אשתפ","אשתתפ","אתחרט","אתעסק","אתפטר","דממת","הסעת","הסתמ","הסתער","הסתר","הסתרת","העסק","הקסמ","השתתפ","השתתפו","חוטפ","חוטפת","חופר","חופרת","חורפ","חטופ","חרוט","טופר","טורח","טורחת","טורט","טורפ","טרחת","טרפו","מדממ","מחטט","מחתרת","מטורפ","מטורפת","מטעה","מסתמ","מסתער","מתחרט","מתעסק","עסקה","פוטר","פוטרת","פורח","פורט","פורע","פטור","פתרת","רוטט","תאתר","תחטופ","תטעה","תעשה","תפוח","תפוטר","תפור","תפטר","תרחמ","תשאפ","תשעה","תשעת","תתפטר"],"difficulty":"easy","counts":{"total":62,"by_length":{"4":41,"5":19,"6":2}}}