{"date":"2027-10-21","version":1,"grid":["חבונו","רבזאו","טסעיר","וחנקא","חייאז"],"answers":["אוויר","אוונ","אוזנ","אויר","אורי","אזעיק","איזו","איזונ","איני","איראנ","אירו","אניח","אנסו","אנסח","אעזוב","אעיר","אעניק","אקיא","אקרא","אקראי","אקריא","ארונ","אריק","ארקנסו","בבונ","בואו","בואי","בטוח","בטוחני","בטחו","בטחי","זבוב","זיונ","זינק","זירו","זעיר","זקני","חוטב","חוסר","חייו","חניונ","חסוי","חרבו","חרבונ","טבעי","טוחנ","יוונ","יורק","יחיו","יחסר","ייקרא","יניח","יניחו","ינסו","יעזבו","יעזוב","יעניק","יקיר","יקרא","יקראו","יקרו","יקרי","יראו","נאקי","נובח","נובע","נורא","נוראי","נזיר","ניוונ","ניזונ","ניחוח","ניקיונ","נעזוב","נעיר","נקרא","נקראו","סבונ","סוחט","סחוט","סנאי","סניור","סרבו","עזבו","עזוב","עיקר","עיקרונ","עיראק","ענקי","קנאי","קניונ","קראו","קראי","קראנו","קרוא","קרונ","ראוי","ראיונ","רואי"],"difficulty":"easy","counts":{"total":99,"by_length":{"4":68,"5":27,"6":4}}}