{"date":"2028-02-05","version":1,"grid":["יגיות","צומיכ","יתפמו","וגזזב","שעטגל"],"answers":["בוכימ","גומות","גומי","גופי","גופימ","גפיימ","זוכימ","זוממ","זוממת","זזתי","טעויות","טעות","יגעו","יובל","יומי","יומיימ","יומית","יופי","ייפגע","ייפגעו","ימות","ימותו","ימימ","ימית","יפגוש","יפגע","יפגעו","יפגשו","יפות","יציג","יתומ","יתומימ","יתוש","יתמוכ","כוזב","כימי","כמויות","כתומ","מבוי","מבוימ","מבוכ","מוזג","מופת","מוצג","מותג","מותו","מותי","מותכ","מזבל","מזויפ","מזויפות","מזויפת","מזלג","מימי","מיפוי","מכות","מכימ","מפגש","מפות","מפיות","מפית","עוגיות","עשוי","עשויות","פגוע","פגוש","פגעו","פגשו","פוגי","פיות","פיתוי","צומת","צופימ","ציות","שגוי","שגויות","שותפ","שותפו","שותפימ","שעות","תגעו","תוכי","תומי","תופימ","תיגע","תיגעו","תיגש","תיפגע","תיפגש","תמות","תמותי","תמימ","תפגוש","תפגע","תפגעו","תפגשו","תציג"],"difficulty":"easy","counts":{"total":97,"by_length":{"5":28,"4":58,"6":10,"7":1}}}